pytest_report_me/__init__.py
pytest_report_me/plugin.py
pytest_report_me/templates/templates.html
pytest_report_me-0.0.4.dist-info/entry_points.txt
pytest_report_me-0.0.4.dist-info/WHEEL
pytest_report_me-0.0.4.dist-info/METADATA
pytest_report_me-0.0.4.dist-info/RECORD
