Metadata-Version: 2.1
Name: pytest-report-me
Version: 0.0.4
Summary: A pytest plugin to generate report.
License: MIT
Author: yuze
Author-email: looker53@sina.com
Requires-Python: >=3.7,<4.0
Classifier: License :: OSI Approved :: MIT License
Classifier: Programming Language :: Python :: 3
Classifier: Programming Language :: Python :: 3.7
Classifier: Programming Language :: Python :: 3.8
Classifier: Programming Language :: Python :: 3.9
Requires-Dist: pytest
